dessia_common/__init__.py
dessia_common/abstract.py
dessia_common/breakdown.py
dessia_common/checks.py
dessia_common/core.py
dessia_common/decorators.py
dessia_common/displays.py
dessia_common/document_generator.py
dessia_common/errors.py
dessia_common/excel_reader.py
dessia_common/exports.py
dessia_common/files.py
dessia_common/forms.py
dessia_common/generation.py
dessia_common/graph.py
dessia_common/measures.py
dessia_common/optimization.py
dessia_common/serialization.py
dessia_common/templates.py
dessia_common/tests.py
dessia_common/typings.py
dessia_common/warnings.py
dessia_common/datatools/__init__.py
dessia_common/datatools/cluster.py
dessia_common/datatools/dataset.py
dessia_common/datatools/metrics.py
dessia_common/datatools/sampling.py
dessia_common/models/__init__.py
dessia_common/models/cars.py
dessia_common/models/power_test.py
dessia_common/models/rand_data.py
dessia_common/models/data/cars.csv
dessia_common/models/data/seed_file.csv
dessia_common/models/workflows/__init__.py
dessia_common/models/workflows/forms_workflow.py
dessia_common/models/workflows/power_simulation.py
dessia_common/models/workflows/workflow_displays.py
dessia_common/models/workflows/workflow_exports.py
dessia_common/models/workflows/workflow_from_file_input.py
dessia_common/schemas/__init__.py
dessia_common/schemas/core.py
dessia_common/schemas/interfaces.py
dessia_common/utils/__init__.py
dessia_common/utils/algebra.py
dessia_common/utils/copy.py
dessia_common/utils/diff.py
dessia_common/utils/helpers.py
dessia_common/utils/interpolation.py
dessia_common/utils/types.py
dessia_common/workflow/__init__.py
dessia_common/workflow/blocks.py
dessia_common/workflow/core.py
dessia_common/workflow/utils.py
dessia_common-0.16.1.dist-info/LICENSE
dessia_common-0.16.1.dist-info/METADATA
dessia_common-0.16.1.dist-info/WHEEL
dessia_common-0.16.1.dist-info/top_level.txt
dessia_common-0.16.1.dist-info/RECORD
