Metadata-Version: 2.1
Name: dessia_common
Version: 0.16.1
Summary: Common tools for DessIA software
Home-page: https://github.com/Dessia-tech/dessia_common
Author: Dessia Technologies SAS
Author-email: root@dessia.tech
Keywords: Dessia,SDK,engineering
Requires-Python: >=3.9
License-File: LICENSE
Requires-Dist: cma
Requires-Dist: dectree
Requires-Dist: docx
Requires-Dist: humanize
Requires-Dist: matplotlib
Requires-Dist: networkx
Requires-Dist: numpy
Requires-Dist: openpyxl
Requires-Dist: orjson >=3.8.0
Requires-Dist: pandas
Requires-Dist: parameterized
Requires-Dist: psutil
Requires-Dist: pyDOE
Requires-Dist: pyDOE2
Requires-Dist: python-docx
Requires-Dist: scikit-learn >=1.2.0
Requires-Dist: scipy
Requires-Dist: typeguard
